ctodd_python_lib_execution-1.0.0.dist-info/LICENSE.txt
ctodd_python_lib_execution-1.0.0.dist-info/METADATA
ctodd_python_lib_execution-1.0.0.dist-info/RECORD
ctodd_python_lib_execution-1.0.0.dist-info/WHEEL
ctodd_python_lib_execution-1.0.0.dist-info/top_level.txt
execution_helpers/__init__.py
execution_helpers/function_executors.py
execution_helpers/tests/__init__.py
execution_helpers/tests/test_function_executors.py
