Metadata-Version: 2.1
Name: ctodd-python-lib-execution
Version: 1.0.0
Summary: Python utilities used for tracking the execution of callables in Python
Home-page: https://github.com/ChristopherHaydenTodd/ctodd-python-lib-execution
Author: Christopher H. Todd
Author-email: Christopher.Hayden.Todd@gmail.com
License: MIT
Keywords: python,libraries,execution,profiling
Platform: UNKNOWN
Classifier: Development Status :: 5 - Production/Stable
Classifier: Intended Audience :: Developers
Classifier: Natural Language :: English
Classifier: Programming Language :: Python
Classifier: Programming Language :: Python :: 3
Classifier: Programming Language :: Python :: 3.6
Classifier: Programming Language :: Python :: 3.7
Classifier: Programming Language :: Python :: 3.8
Requires-Python: >3.6
Requires-Dist: wrapt (>=1.11.1)
